sipcp/__init__.py
sipcp/sipcp.py
sipcp-0.3.1.dist-info/LICENSE
sipcp-0.3.1.dist-info/METADATA
sipcp-0.3.1.dist-info/WHEEL
sipcp-0.3.1.dist-info/entry_points.txt
sipcp-0.3.1.dist-info/top_level.txt
sipcp-0.3.1.dist-info/RECORD
