Metadata-Version: 2.1
Name: sipcp
Version: 0.3.1
Summary: An example program querying the YAPO ontology
Home-page: https://github.com/federicotorrielli/modsem
Author: Federico Torrielli
Author-email: evilscript@protonmail.com
License: UNKNOWN
Platform: UNKNOWN
Classifier: Programming Language :: Python :: 3
Classifier: License :: OSI Approved :: MIT License
Classifier: Operating System :: OS Independent
Requires-Python: >=3.6
Requires-Dist: click (==7.1.2)
Requires-Dist: isodate (==0.6.0)
Requires-Dist: pyparsing (==2.4.7)
Requires-Dist: PyYAML (==5.3.1)
Requires-Dist: rdflib (==5.0.0)
Requires-Dist: six (==1.15.0)
Requires-Dist: typer (==0.3.2)
Requires-Dist: SPARQLWrapper (==1.8.5)
Requires-Dist: fuzzywuzzy (==0.18.0)
Requires-Dist: levenshtein (==0.12.0)
